pyincore/__init__.py
pyincore/baseanalysis.py
pyincore/client.py
pyincore/dataservice.py
pyincore/dataset.py
pyincore/decorators.py
pyincore/dfr3service.py
pyincore/fragilityservice.py
pyincore/globals.py
pyincore/hazardservice.py
pyincore/logging.ini
pyincore/networkdata.py
pyincore/repairservice.py
pyincore/restorationservice.py
pyincore/semanticservice.py
pyincore/spaceservice.py
pyincore/analyses/__init__.py
pyincore/analyses/bridgedamage/__init__.py
pyincore/analyses/bridgedamage/bridgedamage.py
pyincore/analyses/bridgedamage/bridgeutil.py
pyincore/analyses/buildingclusterrecovery/__init__.py
pyincore/analyses/buildingclusterrecovery/buildingclusterrecovery.py
pyincore/analyses/buildingclusterrecovery/buildingdamage.py
pyincore/analyses/buildingclusterrecovery/buildingdata.py
pyincore/analyses/buildingdamage/__init__.py
pyincore/analyses/buildingdamage/buildingdamage.py
pyincore/analyses/buildingdamage/buildingutil.py
pyincore/analyses/buildingeconloss/__init__.py
pyincore/analyses/buildingeconloss/buildingeconloss.py
pyincore/analyses/buildingfunctionality/__init__.py
pyincore/analyses/buildingfunctionality/buildingfunctionality.py
pyincore/analyses/buildingnonstructuraldamage/__init__.py
pyincore/analyses/buildingnonstructuraldamage/buildingnonstructuraldamage.py
pyincore/analyses/buildingnonstructuraldamage/buildingnonstructuralutil.py
pyincore/analyses/buildingstructuraldamage/__init__.py
pyincore/analyses/buildingstructuraldamage/buildingstructuraldamage.py
pyincore/analyses/buildingstructuraldamage/buildingutil.py
pyincore/analyses/buyoutdecision/__init__.py
pyincore/analyses/buyoutdecision/buyoutdecision.py
pyincore/analyses/capitalshocks/__init__.py
pyincore/analyses/capitalshocks/capitalshocks.py
pyincore/analyses/combinedwindwavesurgebuildingdamage/__init__.py
pyincore/analyses/combinedwindwavesurgebuildingdamage/combinedwindwavesurgebuildingdamage.py
pyincore/analyses/combinedwindwavesurgebuildingloss/__init__.py
pyincore-1.22.0.dist-info/licenses/LICENSE
pyincore-1.22.0.dist-info/METADATA
pyincore-1.22.0.dist-info/WHEEL
pyincore-1.22.0.dist-info/top_level.txt
pyincore-1.22.0.dist-info/RECORD
