Metadata-Version: 2.4
Name: pyincore
Version: 1.22.0
Summary: IN-CORE analysis tool python package
Home-page: https://tools.in-core.org
License: Mozilla Public License v2.0
Project-URL: Bug Reports, https://github.com/IN-CORE/pyincore/issues
Project-URL: Source, https://github.com/IN-CORE/pyincore
Keywords: infrastructure,resilience,hazards,data discovery,IN-CORE,earthquake,tsunami,tornado,hurricane,dislocation
Classifier: Development Status :: 4 - Beta
Classifier: Intended Audience :: Science/Research
Classifier: License :: OSI Approved :: Mozilla Public License 2.0 (MPL 2.0)
Classifier: Natural Language :: English
Classifier: Operating System :: OS Independent
Classifier: Programming Language :: Python :: 3
Classifier: Topic :: Scientific/Engineering
Requires-Python: >=3.9
License-File: LICENSE
Requires-Dist: fiona>=1.9.5
Requires-Dist: geopandas>=0.14.0
Requires-Dist: matplotlib>=3.8.0
Requires-Dist: networkx>=3.2.1
Requires-Dist: numpy<2.0a0,>=1.26.0
Requires-Dist: pandas>=2.1.2
Requires-Dist: pyomo<=6.6.2,>=6.0.0
Requires-Dist: pyproj>=3.6.1
Requires-Dist: rasterio>=1.4.2
Requires-Dist: rtree>=1.1.0
Requires-Dist: scipy>=1.11.3
Requires-Dist: shapely>=2.0.2
Requires-Dist: Deprecated>=1.2.14
Provides-Extra: test
Requires-Dist: pycodestyle>=2.6.0; extra == "test"
Requires-Dist: pytest>=3.9.0; extra == "test"
Requires-Dist: python-jose>=3.0; extra == "test"
Dynamic: classifier
Dynamic: description
Dynamic: description-content-type
Dynamic: home-page
Dynamic: keywords
Dynamic: license
Dynamic: license-file
Dynamic: project-url
Dynamic: provides-extra
Dynamic: requires-dist
Dynamic: requires-python
Dynamic: summary
